hestia_earth/validation/__init__.py
hestia_earth/validation/distribution.py
hestia_earth/validation/gee.py
hestia_earth/validation/log.py
hestia_earth/validation/models.py
hestia_earth/validation/preload_requests.py
hestia_earth/validation/terms.py
hestia_earth/validation/utils.py
hestia_earth/validation/version.py
hestia_earth/validation/validators/__init__.py
hestia_earth/validation/validators/aggregated_cycle.py
hestia_earth/validation/validators/aggregated_shared.py
hestia_earth/validation/validators/animal.py
hestia_earth/validation/validators/completeness.py
hestia_earth/validation/validators/cycle.py
hestia_earth/validation/validators/distribution.py
hestia_earth/validation/validators/emission.py
hestia_earth/validation/validators/impact_assessment.py
hestia_earth/validation/validators/indicator.py
hestia_earth/validation/validators/infrastructure.py
hestia_earth/validation/validators/input.py
hestia_earth/validation/validators/management.py
hestia_earth/validation/validators/measurement.py
hestia_earth/validation/validators/organisation.py
hestia_earth/validation/validators/practice.py
hestia_earth/validation/validators/product.py
hestia_earth/validation/validators/property.py
hestia_earth/validation/validators/shared.py
hestia_earth/validation/validators/site.py
hestia_earth/validation/validators/source.py
hestia_earth/validation/validators/transformation.py
hestia_earth_validation-0.37.16.data/scripts/hestia-validate-data
hestia_earth_validation-0.37.16.dist-info/licenses/LICENSE
hestia_earth_validation-0.37.16.dist-info/METADATA
hestia_earth_validation-0.37.16.dist-info/WHEEL
hestia_earth_validation-0.37.16.dist-info/top_level.txt
hestia_earth_validation-0.37.16.dist-info/RECORD
