Metadata-Version: 2.4
Name: hestia_earth_validation
Version: 0.37.16
Summary: HESTIA Data Validation library
Home-page: https://gitlab.com/hestia-earth/hestia-data-validation
Author: Guillaume Royer
Author-email: guillaumeroyer.mail@gmail.com
License: MIT
Keywords: hestia,data,validation
Requires-Python: >=3
License-File: LICENSE
Requires-Dist: hestia-earth-schema>=35.2.0
Requires-Dist: hestia-earth-utils>=0.16.13
Provides-Extra: models
Requires-Dist: hestia-earth-models>=0.75.1; extra == "models"
Provides-Extra: spatial
Requires-Dist: hestia-earth-earth-engine>=0.6.0; extra == "spatial"
Provides-Extra: distribution
Requires-Dist: hestia-earth-distribution>=0.3.1; extra == "distribution"
Dynamic: author
Dynamic: author-email
Dynamic: description
Dynamic: description-content-type
Dynamic: home-page
Dynamic: keywords
Dynamic: license
Dynamic: license-file
Dynamic: provides-extra
Dynamic: requires-dist
Dynamic: requires-python
Dynamic: summary
